setup.py
src/digimat/__init__.py
src/digimat.jobs.egg-info/PKG-INFO
src/digimat.jobs.egg-info/SOURCES.txt
src/digimat.jobs.egg-info/dependency_links.txt
src/digimat.jobs.egg-info/namespace_packages.txt
src/digimat.jobs.egg-info/not-zip-safe
src/digimat.jobs.egg-info/requires.txt
src/digimat.jobs.egg-info/top_level.txt
src/digimat/jobs/__init__.py
src/digimat/jobs/jobs.py