Metadata-Version: 1.0
Name: digimat.jobs
Version: 0.1.4
Summary: Digimat Multithreaded jobs
Home-page: http://www.digimat.ch
Author: Frederic Hess
Author-email: fhess@splust.ch
License: PSF
Platform: UNKNOWN
